{
  "version": 2,
  "extractor": "papercropper",
  "tables": [
    {
      "url": "assets/tables/openreview/openreview-icml-2024-soqxsneui1/table-001.webp",
      "caption": "",
      "page": 0,
      "index": 1,
      "width": 1761,
      "height": 313,
      "label": "Table"
    },
    {
      "url": "assets/tables/openreview/openreview-icml-2024-soqxsneui1/table-002.webp",
      "caption": "",
      "page": 0,
      "index": 2,
      "width": 1774,
      "height": 842,
      "label": "Table"
    },
    {
      "url": "assets/tables/openreview/openreview-icml-2024-soqxsneui1/table-003.webp",
      "caption": "",
      "page": 0,
      "index": 3,
      "width": 1762,
      "height": 522,
      "label": "Table"
    },
    {
      "url": "assets/tables/openreview/openreview-icml-2024-soqxsneui1/table-004.webp",
      "caption": "",
      "page": 0,
      "index": 4,
      "width": 1586,
      "height": 318,
      "label": "Table"
    },
    {
      "url": "assets/tables/openreview/openreview-icml-2024-soqxsneui1/table-005.webp",
      "caption": "",
      "page": 0,
      "index": 5,
      "width": 455,
      "height": 174,
      "label": "Table"
    },
    {
      "url": "assets/tables/openreview/openreview-icml-2024-soqxsneui1/table-006.webp",
      "caption": "",
      "page": 0,
      "index": 6,
      "width": 1297,
      "height": 243,
      "label": "Table"
    }
  ]
}